Metadata-Version: 2.1
Name: jupyterlab
Version: 3.6.8
Summary: JupyterLab computational environment
Home-page: https://jupyter.org
Author: Jupyter Development Team
Author-email: jupyter@googlegroups.com
Keywords: ipython,jupyter
Platform: Linux
Platform: Mac OS X
Platform: Windows
Classifier: Development Status :: 5 - Production/Stable
Classifier: Framework :: Jupyter
Classifier: Framework :: Jupyter :: JupyterLab
Classifier: Framework :: Jupyter :: JupyterLab :: 3
Classifier: Intended Audience :: Developers
Classifier: Intended Audience :: System Administrators
Classifier: Intended Audience :: Science/Research
Classifier: License :: OSI Approved :: BSD License
Classifier: Programming Language :: Python
Classifier: Programming Language :: Python :: 3.7
Classifier: Programming Language :: Python :: 3.8
Classifier: Programming Language :: Python :: 3.9
Classifier: Programming Language :: Python :: 3.10
Classifier: Programming Language :: Python :: 3.11
Requires-Python: >=3.7
License-File: LICENSE
Requires-Dist: ipython
Requires-Dist: packaging
Requires-Dist: tornado>=6.1.0
Requires-Dist: jupyter_core
Requires-Dist: jupyterlab_server~=2.19
Requires-Dist: jupyter_server<3,>=1.16.0
Requires-Dist: jupyter_ydoc~=0.2.4
Requires-Dist: jupyter_server_ydoc~=0.8.0
Requires-Dist: nbclassic
Requires-Dist: notebook<7
Requires-Dist: jinja2>=2.1
Requires-Dist: tomli; python_version < "3.11"
Provides-Extra: test
Requires-Dist: check-manifest; extra == "test"
Requires-Dist: coverage; extra == "test"
Requires-Dist: jupyterlab_server[test]; extra == "test"
Requires-Dist: pre-commit; extra == "test"
Requires-Dist: pytest>=6.0; extra == "test"
Requires-Dist: pytest-cov; extra == "test"
Requires-Dist: pytest-console-scripts; extra == "test"
Requires-Dist: pytest-check-links>=0.5; extra == "test"
Requires-Dist: pytest-jupyter>=0.5.3; extra == "test"
Requires-Dist: requests; extra == "test"
Requires-Dist: requests_cache; extra == "test"
Requires-Dist: virtualenv; extra == "test"
Provides-Extra: docs
Requires-Dist: sphinx>=1.8; extra == "docs"
Requires-Dist: sphinx-copybutton; extra == "docs"
Requires-Dist: sphinx_rtd_theme; extra == "docs"
Requires-Dist: pytest; extra == "docs"
Requires-Dist: pytest-tornasync; extra == "docs"
Requires-Dist: pytest-check-links; extra == "docs"
Requires-Dist: jsx-lexer; extra == "docs"
Requires-Dist: myst-parser; extra == "docs"
